visiannot/__init__.py
visiannot/__main__.py
visiannot/configuration/Configuration.py
visiannot/configuration/ConfigurationWindow.py
visiannot/configuration/__init__.py
visiannot/configuration/update.py
visiannot/tools/__init__.py
visiannot/tools/audio_loader.py
visiannot/tools/data_loader.py
visiannot/tools/datetime_converter.py
visiannot/tools/pyqt_overlayer.py
visiannot/tools/pyqtgraph_overlayer.py
visiannot/tools/video_loader.py
visiannot/visiannot/ViSiAnnoT.py
visiannot/visiannot/ViSiAnnoTLongRec.py
visiannot/visiannot/ViSiAnnoTLongRecFromConfigFile.py
visiannot/visiannot/ViSiAnnoTLongRecFromConfigGUI.py
visiannot/visiannot/__init__.py
visiannot/visiannot/components/AnnotEventWidget.py
visiannot/visiannot/components/AnnotImageWidget.py
visiannot/visiannot/components/CustomTemporalRangeWidget.py
visiannot/visiannot/components/FileSelectionWidget.py
visiannot/visiannot/components/FromCursorTemporalRangeWidget.py
visiannot/visiannot/components/LogoWidgets.py
visiannot/visiannot/components/MenuBar.py
visiannot/visiannot/components/ProgressWidget.py
visiannot/visiannot/components/Signal.py
visiannot/visiannot/components/SignalWidget.py
visiannot/visiannot/components/TruncTemporalRangeWidget.py
visiannot/visiannot/components/VideoWidget.py
visiannot/visiannot/components/WindowsPopUp.py
visiannot/visiannot/components/__init__.py
visiannot/visiannot/components/Images/DIGI-NEWB.jpg
visiannot/visiannot/components/Images/next.jpg
visiannot/visiannot/components/Images/previous.jpg
visiannot/visiannot/components/Images/visibility.jpg
visiannot/visiannot/components/Images/zoomin.jpg
visiannot/visiannot/components/Images/zoomout.jpg
visiannot-0.2.8.dist-info/LICENSE.txt
visiannot-0.2.8.dist-info/METADATA
visiannot-0.2.8.dist-info/WHEEL
visiannot-0.2.8.dist-info/top_level.txt
visiannot-0.2.8.dist-info/RECORD
