Metadata-Version: 2.1
Name: visiannot
Version: 0.2.8
Summary: Graphical user interface for visualization and annotation of video and signal data
Home-page: https://github.com/RphWbr/visiannot
Author: Raphael Weber
Author-email: raphael.weber@univ-rennes1.fr
License: CeCILL
Platform: UNKNOWN
Classifier: Development Status :: 4 - Beta
Classifier: Operating System :: OS Independent
Classifier: Intended Audience :: Science/Research
Classifier: Programming Language :: Python :: 3
Classifier: Programming Language :: Python :: 3.7
Classifier: Programming Language :: Python :: 3.8
Classifier: Programming Language :: Python :: 3.9
Classifier: License :: OSI Approved :: CEA CNRS Inria Logiciel Libre License, version 2.1 (CeCILL-2.1)
Requires-Python: >=3.6, <4
License-File: LICENSE.txt
Requires-Dist: configobj (>=5.0.6)
Requires-Dist: opencv-python (<4.0.0.21,>=3.4.8.29)
Requires-Dist: h5py (>=2.10.0)
Requires-Dist: numpy (>=1.18.5)
Requires-Dist: PyQt5 (>=5.14.1)
Requires-Dist: pyqtgraph (>=0.11.0)
Requires-Dist: pytz (>=2019.3)
Requires-Dist: scipy (>=1.5.3)
Requires-Dist: tinytag (>=1.7.0)
